{"page":"policyList","count":1,"policyList":[{"_id":"68312de974b32ef6da2bb7fd","policy_number":"YEEX9MOIBU7X","account_id":{"_id":"68312de7418eb50690c8cc3c","account_name":"Lura Lucca & Owen Dodson"},"account_type":"Commercial","agent_id":{"_id":"68312de7418eb50690c8c7ba","agent":"Alex Watson"},"category_id":{"_id":"68312de7418eb50690c8d118","category_name":"Commercial Auto"},"company_id":{"_id":"68312de7418eb50690c8d0e9","company_name":"Integon Gen Ins Corp"},"csr":"Tami Ellison","policy_end_date":"2019-11-02T00:00:00.000Z","policy_mode":"12","policy_start_date":"2018-11-02T00:00:00.000Z","policy_type":"Single","premium_amount":"1180.83","premium_amount_written":"","producer":"Brandie Placencia","user_id":{"_id":"68312de7418eb50690c8c7be","email":"madler@yahoo.ca","userType":"Active Client","firstname":"Lura Lucca","address":"170 MATTHIAS CT","phone":"8677356559","state":"NC","city":"MOCKSVILLE","zip":"27028","gender":"","dob":"1960-02-11T00:00:00.000Z"}}]}